swapslib/__init__.py
swapslib/defaults.py
swapslib-0.0.1.dist-info/LICENSE
swapslib-0.0.1.dist-info/METADATA
swapslib-0.0.1.dist-info/WHEEL
swapslib-0.0.1.dist-info/top_level.txt
swapslib-0.0.1.dist-info/RECORD
