Metadata-Version: 2.1
Name: swapslib
Version: 0.0.1
Summary: Coding Interest Rate Derivatives
Author: J H M Darbyshire
License: Attribution-NonCommercial-NoDerivatives 4.0 International
Project-URL: Homepage, https://github.com/attack68/TBD
Keywords: interest rate,derivatives,swaps
Requires-Python: >=3.7
License-File: LICENSE
Requires-Dist: numpy (>=1.21.5)
Requires-Dist: scipy (>=1.8.0)
Requires-Dist: matplotlib (>=3.5.1)
Requires-Dist: pandas (>=1.4.1)
Provides-Extra: dev
Requires-Dist: pytest (>=7.0.1) ; extra == 'dev'
Requires-Dist: jupyterlab (>=3.3.1) ; extra == 'dev'
Requires-Dist: matplotlib (>=3.5.1) ; extra == 'dev'
Requires-Dist: numba (>=0.55.1) ; extra == 'dev'
Requires-Dist: pandas (>=1.4.1) ; extra == 'dev'
Requires-Dist: sphinx (>=5.1.1) ; extra == 'dev'
